pynyhtm.cpython-39-aarch64-linux-gnu.so
pynyhtm-0.1.0.dist-info/WHEEL
pynyhtm-0.1.0.dist-info/LICENCE
pynyhtm-0.1.0.dist-info/top_level.txt
pynyhtm-0.1.0.dist-info/RECORD
pynyhtm-0.1.0.dist-info/METADATA
