Metadata-Version: 2.1
Name: pynyhtm
Version: 0.1.0
Summary: Python wrapper for the libtinyhtm library.
Author-email: Till <till@fleisch.dev>
License: # PynyHTM license
Project-URL: Homepage, https://github.com/TillFleisch/PynyHTM
Project-URL: Repository, https://github.com/TillFleisch/PynyHTM.git
Project-URL: Issues, https://github.com/TillFleisch/PynyHTM/issues
Keywords: htm,libtinyhtm,hierarchial triangular mesh,triangle subdivision,index
License-File: LICENCE
Requires-Dist: numpy
Requires-Dist: tomli; python_version < "3.11"
Provides-Extra: dev
Requires-Dist: black; extra == "dev"
Requires-Dist: isort; extra == "dev"
Requires-Dist: pytest; extra == "dev"
